jijzept/_version.py
jijzept/__init__.py
jijzept/__marker__.cpython-39-darwin.so
jijzept/post_api/__init__.py
jijzept/post_api/post_api.py
jijzept/post_api/__pycache__/__init__.cpython-39.pyc
jijzept/post_api/__pycache__/post_api.cpython-39.opt-1.pyc
jijzept/post_api/__pycache__/__init__.cpython-39.opt-1.pyc
jijzept/post_api/__pycache__/post_api.cpython-39.pyc
jijzept/response/jmresponse.py
jijzept/response/__init__.py
jijzept/response/base.py
jijzept/response/__pycache__/__init__.cpython-39.pyc
jijzept/response/__pycache__/jmresponse.cpython-39.pyc
jijzept/response/__pycache__/__init__.cpython-39.opt-1.pyc
jijzept/response/__pycache__/base.cpython-39.pyc
jijzept/response/__pycache__/jmresponse.cpython-39.opt-1.pyc
jijzept/response/__pycache__/base.cpython-39.opt-1.pyc
jijzept/instance_translator/instance_translator.py
jijzept/instance_translator/__init__.py
jijzept/instance_translator/__pycache__/__init__.cpython-39.pyc
jijzept/instance_translator/__pycache__/instance_translator.cpython-39.pyc
jijzept/instance_translator/__pycache__/__init__.cpython-39.opt-1.pyc
jijzept/instance_translator/__pycache__/instance_translator.cpython-39.opt-1.pyc
jijzept/config/path_type.py
jijzept/config/__init__.py
jijzept/config/handle_config.py
jijzept/config/__pycache__/__init__.cpython-39.pyc
jijzept/config/__pycache__/__init__.cpython-39.opt-1.pyc
jijzept/config/__pycache__/path_type.cpython-39.pyc
jijzept/config/__pycache__/handle_config.cpython-39.pyc
jijzept/config/__pycache__/path_type.cpython-39.opt-1.pyc
jijzept/config/__pycache__/handle_config.cpython-39.opt-1.pyc
jijzept/entity/__init__.py
jijzept/entity/schema.py
jijzept/entity/__pycache__/__init__.cpython-39.pyc
jijzept/entity/__pycache__/schema.cpython-39.opt-1.pyc
jijzept/entity/__pycache__/schema.cpython-39.pyc
jijzept/entity/__pycache__/__init__.cpython-39.opt-1.pyc
jijzept/utils/__init__.py
jijzept/utils/utils.py
jijzept/utils/__pycache__/__init__.cpython-39.pyc
jijzept-1.18.5.dist-info/RECORD
jijzept-1.18.5.dist-info/WHEEL
jijzept-1.18.5.dist-info/entry_points.txt
jijzept-1.18.5.dist-info/top_level.txt
jijzept-1.18.5.dist-info/LICENSE.txt
jijzept-1.18.5.dist-info/METADATA
