Metadata-Version: 2.1
Name: jijzept
Version: 1.18.5
Summary: Python Interface for Jij-Zept.
Home-page: https://www.jijzept.com
Author: Jij Inc.
Author-email: info@j-ij.com
License: Other/Proprietary License
Project-URL: Documentation, https://www.documentation.jijzept.com
Project-URL: Reference, https://www.ref.documentation.jijzept.com
Project-URL: JijModeling, https://pypi.org/project/jijmodeling/
Classifier: Programming Language :: Python :: 3.9
Classifier: Programming Language :: Python :: 3.10
Classifier: Programming Language :: Python :: 3.11
Classifier: Programming Language :: Python :: 3 :: Only
Classifier: Programming Language :: Python :: Implementation :: CPython
Classifier: Operating System :: Microsoft :: Windows
Classifier: Operating System :: POSIX
Classifier: Operating System :: MacOS
Requires-Python: <3.12,>=3.9
License-File: LICENSE.txt
Requires-Dist: jijmodeling<2.0.0,>=1.1.1
Requires-Dist: numpy<1.25.0
Requires-Dist: requests<2.34.0
Requires-Dist: toml<0.11.0
Requires-Dist: zstandard<0.30.0,>0.10.0
Requires-Dist: pydantic<3.0.0,>=2.0.0
Requires-Dist: python-rapidjson<2.0,>=1.0
Requires-Dist: click<8.2.0
Requires-Dist: protobuf<6.0,>=3.20
Provides-Extra: test
Requires-Dist: Cython; extra == "test"
Requires-Dist: pytest; extra == "test"
Requires-Dist: pytest-mock; extra == "test"
Requires-Dist: pytest-cov; extra == "test"
Requires-Dist: pytest-html; extra == "test"
Requires-Dist: pytest-randomly; extra == "test"
Requires-Dist: pytest-clarity; extra == "test"
Requires-Dist: pytest-cython; extra == "test"
